{
  "required": true,
  "minVersion": "0.8",
  "package": "pm.n2.tangerine.mixin",
  "compatibilityLevel": "JAVA_17",
  "client": [
    "AbstractBlockMixin",
    "AbstractClientPlayerEntityMixin",
    "BlockMixin",
    "BoatEntityAccessor",
    "ClientChunkManagerAccessor",
    "ClientChunkMapAccessor",
    "ClientPlayerEntityMixin",
    "ClientPlayerInteractionManagerMixin",
    "EntityMixin",
    "FluidBlockMixin",
    "InputMixin",
    "KeyboardMixin",
    "LivingEntityMixin",
    "MinecraftClientMixin",
    "MouseMixin",
    "PlayerMoveC2SPacketMixin",
    "TitleScreenMixin",
    "WorldChunkMixin"
  ],
  "injectors": {
    "defaultRequire": 1
  }
}
